proxyot/__init__.py
proxyot/proxyot.py
proxyot-0.0.4.dist-info/LICENSE
proxyot-0.0.4.dist-info/METADATA
proxyot-0.0.4.dist-info/WHEEL
proxyot-0.0.4.dist-info/top_level.txt
proxyot-0.0.4.dist-info/RECORD
