Metadata-Version: 2.1
Name: proxyot
Version: 0.0.4
Summary: Access the values of your ProxyOT points and lists.
Author: OchaTEK
Author-email: <ochatek@ochatek.com>
Keywords: python,proxyot,iot
Classifier: Development Status :: 1 - Planning
Classifier: Intended Audience :: Developers
Classifier: Programming Language :: Python :: 3
Classifier: Operating System :: Unix
Classifier: Operating System :: MacOS :: MacOS X
Classifier: Operating System :: Microsoft :: Windows
License-File: LICENSE
Requires-Dist: requests
